kebe_ship/__init__.py
kebe_ship/assets.py
kebe_ship/data/tars/prometheus-cpp.tgz
kebe_ship-0.0.22.dist-info/licenses/LICENSE
kebe_ship-0.0.22.dist-info/METADATA
kebe_ship-0.0.22.dist-info/WHEEL
kebe_ship-0.0.22.dist-info/top_level.txt
kebe_ship-0.0.22.dist-info/RECORD
