Metadata-Version: 2.4
Name: kebe-ship
Version: 0.0.22
Summary: Example package that bundles data files.
Author: Your Name
License: MIT License
Classifier: Programming Language :: Python :: 3
Classifier: License :: OSI Approved :: MIT License
Requires-Python: >=3.9
License-File: LICENSE
Dynamic: license-file
